SwiftViperGenerator-1.1.0.dist-info/METADATA
SwiftViperGenerator-1.1.0.dist-info/RECORD
SwiftViperGenerator-1.1.0.dist-info/WHEEL
SwiftViperGenerator-1.1.0.dist-info/entry_points.txt
SwiftViperGenerator-1.1.0.dist-info/top_level.txt
swivigen/__init__.py
swivigen/Common/AbstractPresenter.swift
swivigen/Common/AbstractRouter.swift
swivigen/Common/TabBarRouter.swift
swivigen/Common/ViperController.swift
swivigen/Common/ViperTabBarController.swift
swivigen/Templates/Controller.tpl.swift
swivigen/Templates/Header.tpl.swift
swivigen/Templates/Interactor.tpl.swift
swivigen/Templates/Presenter.tpl.swift
swivigen/Templates/Router.tpl.swift
swivigen/Templates/View.tpl.swift
