Metadata-Version: 2.1
Name: SwiftViperGenerator
Version: 1.1.0
Summary: VIPER boilerplate code generator for Swift XCode projects
Home-page: http://github.com/bivanov/swiftvipergenerator
Author: Bohdan Ivanov
Author-email: bogdanivanov@live.com
License: MIT
Keywords: build development
Platform: UNKNOWN
Classifier: Development Status :: 4 - Beta
Classifier: Intended Audience :: Developers
Classifier: Topic :: Utilities
Classifier: License :: OSI Approved :: MIT License
Classifier: Programming Language :: Python :: 3
Classifier: Programming Language :: Python :: 3.2
Classifier: Programming Language :: Python :: 3.3
Classifier: Programming Language :: Python :: 3.4
Classifier: Programming Language :: Python :: 3.5
Classifier: Programming Language :: Python :: 3.6
Requires-Dist: pbxproj
Requires-Dist: jinja2
Requires-Dist: pyyaml
Requires-Dist: colorama
